kagiso_auth/__init__.py
kagiso_auth/admin.py
kagiso_auth/auth_api_client.py
kagiso_auth/backends.py
kagiso_auth/exceptions.py
kagiso_auth/forms.py
kagiso_auth/http.py
kagiso_auth/managers.py
kagiso_auth/models.py
kagiso_auth/settings.py
kagiso_auth/urls.py
kagiso_auth/utils.py
kagiso_auth/views.py
kagiso_auth/migrations/0001_initial.py
kagiso_auth/migrations/0002_auto_20150421_0835.py
kagiso_auth/migrations/0003_kagisouser_profile.py
kagiso_auth/migrations/0004_auto_20150422_0903.py
kagiso_auth/migrations/0005_kagisouser_email_confirmed.py
kagiso_auth/migrations/0006_auto_20150514_1045.py
kagiso_auth/migrations/0007_auto_20151130_1043.py
kagiso_auth/migrations/0008_auto_20160112_0817.py
kagiso_auth/migrations/__init__.py
kagiso_auth/templates/base.html
kagiso_auth/templates/kagiso_auth/blank.html
kagiso_auth/templates/kagiso_auth/forgot_password.html
kagiso_auth/templates/kagiso_auth/reset_password.html
kagiso_auth/templates/kagiso_auth/sign_in.html
kagiso_auth/templates/kagiso_auth/sign_up.html
kagiso_auth/templates/kagiso_auth/update_details.html
kagiso_auth/tests/__init__.py
kagiso_auth/tests/test_utils.py
kagiso_auth/tests/integration/__init__.py
kagiso_auth/tests/integration/test_integration.py
kagiso_auth/tests/integration/utils.py
kagiso_auth/tests/settings/__init__.py
kagiso_auth/tests/settings/ci.py
kagiso_auth/tests/settings/test.py
kagiso_auth/tests/unit/__init__.py
kagiso_auth/tests/unit/mocks.py
kagiso_auth/tests/unit/test_auth_api_client.py
kagiso_auth/tests/unit/test_backends.py
kagiso_auth/tests/unit/test_forms.py
kagiso_auth/tests/unit/test_managers.py
kagiso_auth/tests/unit/test_models.py
kagiso_auth/tests/unit/test_views.py
kagiso_django_auth-9.2.2.dist-info/DESCRIPTION.rst
kagiso_django_auth-9.2.2.dist-info/METADATA
kagiso_django_auth-9.2.2.dist-info/RECORD
kagiso_django_auth-9.2.2.dist-info/WHEEL
kagiso_django_auth-9.2.2.dist-info/metadata.json
kagiso_django_auth-9.2.2.dist-info/top_level.txt
