Metadata-Version: 2.0
Name: kagiso-django-auth
Version: 9.2.2
Summary: Kagiso Django AuthBackend
Home-page: https://github.com/Kagiso-Future-Media/django_auth
Author: Kagiso Media
Author-email: development@kagiso.io
License: UNKNOWN
Platform: UNKNOWN
Requires-Dist: authomatic (==0.1.0.post1)
Requires-Dist: jsonfield (==1.0.3)
Requires-Dist: requests (==2.10.0)
